odoo8_addon_business_requirement_earned_value-8.0.1.0.0-py2.7-nspkg.pth
odoo8_addon_business_requirement_earned_value-8.0.1.0.0.dist-info/DESCRIPTION.rst
odoo8_addon_business_requirement_earned_value-8.0.1.0.0.dist-info/METADATA
odoo8_addon_business_requirement_earned_value-8.0.1.0.0.dist-info/RECORD
odoo8_addon_business_requirement_earned_value-8.0.1.0.0.dist-info/WHEEL
odoo8_addon_business_requirement_earned_value-8.0.1.0.0.dist-info/metadata.json
odoo8_addon_business_requirement_earned_value-8.0.1.0.0.dist-info/namespace_packages.txt
odoo8_addon_business_requirement_earned_value-8.0.1.0.0.dist-info/top_level.txt
odoo_addons/business_requirement_earned_value/README.rst
odoo_addons/business_requirement_earned_value/__init__.py
odoo_addons/business_requirement_earned_value/__openerp__.py
odoo_addons/business_requirement_earned_value/report/__init__.py
odoo_addons/business_requirement_earned_value/report/br_earned_value_report.py
odoo_addons/business_requirement_earned_value/report/br_earned_value_report_view.xml
odoo_addons/business_requirement_earned_value/security/ir.model.access.csv
